command_line_menu/__init__.py
command_line_menu/menu.py
Command_Line_Menu-0.2.2.dist-info/LICENSE.txt
Command_Line_Menu-0.2.2.dist-info/METADATA
Command_Line_Menu-0.2.2.dist-info/WHEEL
Command_Line_Menu-0.2.2.dist-info/top_level.txt
Command_Line_Menu-0.2.2.dist-info/RECORD
