Metadata-Version: 2.1
Name: Command-Line-Menu
Version: 0.2.2
Summary: A simple module to create a menu for command line programs.
Home-page: https://github.com/KrazyKirby99999/command-line-menu
Author: KrazyKirby99999
Author-email: krazykirby99999@gmail.com
License: GNU AGPLv3
Platform: UNKNOWN
